snmpsim_control_plane/__init__.py
snmpsim_control_plane/commands/__init__.py
snmpsim_control_plane/commands/importer.py
snmpsim_control_plane/commands/management.py
snmpsim_control_plane/commands/metrics.py
snmpsim_control_plane/commands/supervisor.py
snmpsim_control_plane/daemon.py
snmpsim_control_plane/error.py
snmpsim_control_plane/log.py
snmpsim_control_plane/management/__init__.py
snmpsim_control_plane/management/config.py
snmpsim_control_plane/management/exporters/__init__.py
snmpsim_control_plane/management/exporters/builder.py
snmpsim_control_plane/management/exporters/renderer.py
snmpsim_control_plane/management/exporters/templates/snmpsim-command-responder.j2
snmpsim_control_plane/management/models.py
snmpsim_control_plane/management/recording.py
snmpsim_control_plane/management/schemas.py
snmpsim_control_plane/management/views.py
snmpsim_control_plane/metrics/__init__.py
snmpsim_control_plane/metrics/config.py
snmpsim_control_plane/metrics/importers/__init__.py
snmpsim_control_plane/metrics/importers/process.py
snmpsim_control_plane/metrics/importers/snmpagent.py
snmpsim_control_plane/metrics/manager.py
snmpsim_control_plane/metrics/models.py
snmpsim_control_plane/metrics/reader.py
snmpsim_control_plane/metrics/schemas.py
snmpsim_control_plane/metrics/utils.py
snmpsim_control_plane/metrics/views.py
snmpsim_control_plane/supervisor/__init__.py
snmpsim_control_plane/supervisor/lifecycle.py
snmpsim_control_plane/supervisor/manager.py
snmpsim_control_plane/supervisor/reporting/__init__.py
snmpsim_control_plane/supervisor/reporting/collector.py
snmpsim_control_plane/supervisor/reporting/formats/__init__.py
snmpsim_control_plane/supervisor/reporting/formats/base.py
snmpsim_control_plane/supervisor/reporting/formats/jsondoc.py
snmpsim_control_plane/supervisor/reporting/formats/null.py
snmpsim_control_plane/supervisor/reporting/manager.py
snmpsim_control_plane/wsgi/__init__.py
snmpsim_control_plane/wsgi/management.py
snmpsim_control_plane/wsgi/metrics.py
snmpsim_control_plane_lextudio-0.0.3.dist-info/entry_points.txt
snmpsim_control_plane_lextudio-0.0.3.dist-info/LICENSE.txt
snmpsim_control_plane_lextudio-0.0.3.dist-info/WHEEL
snmpsim_control_plane_lextudio-0.0.3.dist-info/METADATA
snmpsim_control_plane_lextudio-0.0.3.dist-info/RECORD
